odoo/addons/l10n_fr_account_invoice_facturx/README.rst
odoo/addons/l10n_fr_account_invoice_facturx/__init__.py
odoo/addons/l10n_fr_account_invoice_facturx/__manifest__.py
odoo/addons/l10n_fr_account_invoice_facturx/i18n/fr.po
odoo/addons/l10n_fr_account_invoice_facturx/i18n/l10n_fr_account_invoice_factur-x.pot
odoo/addons/l10n_fr_account_invoice_facturx/i18n/l10n_fr_account_invoice_facturx.pot
odoo/addons/l10n_fr_account_invoice_facturx/models/__init__.py
odoo/addons/l10n_fr_account_invoice_facturx/models/account_move.py
odoo/addons/l10n_fr_account_invoice_facturx/readme/CONTRIBUTORS.rst
odoo/addons/l10n_fr_account_invoice_facturx/readme/DESCRIPTION.rst
odoo/addons/l10n_fr_account_invoice_facturx/static/description/icon.png
odoo/addons/l10n_fr_account_invoice_facturx/static/description/index.html
odoo14_addon_l10n_fr_account_invoice_facturx-14.0.1.0.1.dev6.dist-info/METADATA
odoo14_addon_l10n_fr_account_invoice_facturx-14.0.1.0.1.dev6.dist-info/WHEEL
odoo14_addon_l10n_fr_account_invoice_facturx-14.0.1.0.1.dev6.dist-info/top_level.txt
odoo14_addon_l10n_fr_account_invoice_facturx-14.0.1.0.1.dev6.dist-info/RECORD
